synapse/__init__.py
synapse/axon.py
synapse/cells.py
synapse/common.py
synapse/cortex.py
synapse/cryotank.py
synapse/daemon.py
synapse/datamodel.py
synapse/exc.py
synapse/glob.py
synapse/mindmeld.py
synapse/telepath.py
synapse/cmds/__init__.py
synapse/cmds/boss.py
synapse/cmds/cortex.py
synapse/cmds/hive.py
synapse/data/__init__.py
synapse/data/iana.tlds.mpk
synapse/data/iana.uris.mpk
synapse/data/attack-flow/LICENSE.txt
synapse/data/attack-flow/README.md
synapse/data/attack-flow/attack-flow-schema-2.0.0.json
synapse/data/certs/cas/The Vertex Project Intermediate CA 00.crt
synapse/data/certs/cas/The Vertex Project ROOT CA.crt
synapse/data/certs/crls/The Vertex Project Intermediate CA 00.crl
synapse/data/certs/crls/The Vertex Project ROOT CA.crl
synapse/data/jsonschemas/README.md
synapse/data/jsonschemas/json-schema.org/draft-07/schema
synapse/data/jsonschemas/raw.githubusercontent.com/oasis-open/LICENSE.txt
synapse/data/jsonschemas/raw.githubusercontent.com/oasis-open/cti-stix2-json-schemas/stix2.1/schemas/common/binary.json
synapse/data/jsonschemas/raw.githubusercontent.com/oasis-open/cti-stix2-json-schemas/stix2.1/schemas/common/bundle.json
synapse/data/jsonschemas/raw.githubusercontent.com/oasis-open/cti-stix2-json-schemas/stix2.1/schemas/common/core.json
synapse/data/jsonschemas/raw.githubusercontent.com/oasis-open/cti-stix2-json-schemas/stix2.1/schemas/common/cyber-observable-core.json
synapse/data/jsonschemas/raw.githubusercontent.com/oasis-open/cti-stix2-json-schemas/stix2.1/schemas/common/dictionary.json
synapse/data/jsonschemas/raw.githubusercontent.com/oasis-open/cti-stix2-json-schemas/stix2.1/schemas/common/extension-definition.json
synapse/data/jsonschemas/raw.githubusercontent.com/oasis-open/cti-stix2-json-schemas/stix2.1/schemas/common/extension.json
synapse/data/jsonschemas/raw.githubusercontent.com/oasis-open/cti-stix2-json-schemas/stix2.1/schemas/common/external-reference.json
synapse-2.231.0.dist-info/licenses/LICENSE
synapse-2.231.0.dist-info/METADATA
synapse-2.231.0.dist-info/WHEEL
synapse-2.231.0.dist-info/top_level.txt
synapse-2.231.0.dist-info/RECORD
